MANIFEST.in
setup.py
ppss_scss/__init__.py
ppss_scss/views.py
ppss_scss.egg-info/PKG-INFO
ppss_scss.egg-info/SOURCES.txt
ppss_scss.egg-info/dependency_links.txt
ppss_scss.egg-info/requires.txt
ppss_scss.egg-info/top_level.txt