Metadata-Version: 1.0
Name: ppss-scss
Version: 0.3.2
Summary: simple scsscompiler for pyramid
Home-page: http://www.pingpongstars.it
Author: pdepmcp
Author-email: d.cariboni@pingpongstars.it
License: UNKNOWN
Platform: UNKNOWN
